pyenigma/__init__.py
pyenigma/_enigma.cpython-39-x86_64-linux-gnu.so
pyenigma/_enigma.c
libenigma-0.0.1.dist-info/RECORD
libenigma-0.0.1.dist-info/METADATA
libenigma-0.0.1.dist-info/WHEEL
libenigma-0.0.1.dist-info/top_level.txt
